README.md
setup.py
jsonizer/__init__.py
jsonizer/cleaner.py
jsonizer/extractor.py
jsonizer/jsonize.py
jsonizer/model.py
safari_bookmarks_jsonize.egg-info/PKG-INFO
safari_bookmarks_jsonize.egg-info/SOURCES.txt
safari_bookmarks_jsonize.egg-info/dependency_links.txt
safari_bookmarks_jsonize.egg-info/entry_points.txt
safari_bookmarks_jsonize.egg-info/requires.txt
safari_bookmarks_jsonize.egg-info/top_level.txt