Metadata-Version: 1.2
Name: safari-bookmarks-jsonize
Version: 1.0.2
Summary: transform Safari bookmarks export to JSON file
Home-page: https://github.com/Monsoir/safari-bookmarks-jsonizer
Author: Monsoir
Author-email: monwingyeung@gmail.com
License: MIT License
Keywords: Safari,Bookmarks,JSON,Monsoir
Platform: any
Classifier: Programming Language :: Python :: 3.6
Requires-Python: >=3
